MANIFEST.in
README.txt
setup.py
docs/HISTORY.txt
docs/LICENSE.txt
src/silva/__init__.py
src/silva.app.document.egg-info/PKG-INFO
src/silva.app.document.egg-info/SOURCES.txt
src/silva.app.document.egg-info/dependency_links.txt
src/silva.app.document.egg-info/namespace_packages.txt
src/silva.app.document.egg-info/requires.txt
src/silva.app.document.egg-info/top_level.txt
src/silva.app.document.egg-info/zip-safe
src/silva/app/__init__.py
src/silva/app/document/__init__.py
src/silva/app/document/configure.zcml
src/silva/app/document/document.png
src/silva/app/document/document.py
src/silva/app/document/feed.py
src/silva/app/document/ftesting.zcml
src/silva/app/document/interfaces.py
src/silva/app/document/testing.py
src/silva/app/document/transform.py
src/silva/app/document/document_templates/documentpublicview.cpt
src/silva/app/document/silvaxml/__init__.py
src/silva/app/document/silvaxml/xmlexport.py
src/silva/app/document/silvaxml/xmlimport.py
src/silva/app/document/tests/__init__.py
src/silva/app/document/tests/test_document.py
src/silva/app/document/tests/test_transform.py
src/silva/app/document/tests/test_view.py
src/silva/app/document/tests/test_xml_export.py
src/silva/app/document/tests/test_xml_import.py
src/silva/app/document/tests/data/content-listing.png
src/silva/app/document/tests/data/test_export_multiple.silvaxml
src/silva/app/document/tests/data/test_export_reference.silvaxml
src/silva/app/document/tests/data/test_export_reference_broken.silvaxml
src/silva/app/document/tests/data/test_export_reference_external.silvaxml
src/silva/app/document/tests/data/test_import_anchor.silvaxml
src/silva/app/document/tests/data/test_import_document.silvaxml
src/silva/app/document/tests/data/test_import_reference.silvaxml
src/silva/app/document/tests/data/test_import_reference_broken.silvaxml