Metadata-Version: 1.1
Name: silva.app.document
Version: 3.0.2
Summary: Document content for Silva 3.x with WYSIWYG Editor
Home-page: https://github.com/silvacms/silva.app.document
Author: Antonin Amand
Author-email: info@infrae.com
License: BSD
Keywords: document silva wysiwyg
Platform: UNKNOWN
Classifier: Programming Language :: Python
